Hydrogen_Station/__init__.py
Hydrogen_Station/electrolyzer_model.py
Hydrogen_Station/electrolyzer_model_old.py
Hydrogen_Station/get2fa.py
Hydrogen_Station/h2_storage.py
Hydrogen_Station/karamay_pvwattsv8.py
Hydrogen_Station/load_generation.py
Hydrogen_Station/oxygen_liquid.py
Hydrogen_Station/pem_fuelcell_model.py
Hydrogen_Station/time_calculation.py
tests/__init__.py
tests/hydrogen_station_all.py
tests/test.py
Hydrogen_energy_storage_power_station-0.1.7.dist-info/METADATA
Hydrogen_energy_storage_power_station-0.1.7.dist-info/WHEEL
Hydrogen_energy_storage_power_station-0.1.7.dist-info/top_level.txt
Hydrogen_energy_storage_power_station-0.1.7.dist-info/RECORD
