Metadata-Version: 2.1
Name: Hydrogen-energy-storage-power-station
Version: 0.1.7
Summary: It is a simple model for hydrogen power station
Home-page: https://github.com/JunchiMA/Hydrogen_Station
Author: Junchi Ma
Author-email: junchima@outlook.com
License: MIT
